safeint.py
safeint-0.0.4.dist-info/DESCRIPTION.rst
safeint-0.0.4.dist-info/METADATA
safeint-0.0.4.dist-info/RECORD
safeint-0.0.4.dist-info/WHEEL
safeint-0.0.4.dist-info/metadata.json
safeint-0.0.4.dist-info/top_level.txt
