Metadata-Version: 2.0
Name: safeint
Version: 0.0.4
Summary: Create an integer within a range.
Home-page: https://github.com/pelotoncycle/safeint
Author: Dan Sokolsky
Author-email: dan@pelotoncycle.com
License: MIT
Keywords: int development security
Platform: UNKNOWN
Classifier: Development Status :: 3 - Alpha
Classifier: Intended Audience :: Developers
Classifier: Topic :: Software Development
Classifier: License :: OSI Approved :: MIT License
Classifier: Programming Language :: Python :: 2
Classifier: Programming Language :: Python :: 3
Requires-Dist: six
Provides-Extra: dev
Requires-Dist: check-manifest; extra == 'dev'
Provides-Extra: test
Requires-Dist: coverage; extra == 'test'
Requires-Dist: flake8; extra == 'test'
Requires-Dist: pytest; extra == 'test'
Requires-Dist: pytest-cov; extra == 'test'
